{
  "metadata": {
    "description": "Aggregate demographic data on open-source contributors from published surveys and research",
    "last_updated": "2026-03-28",
    "verified": "2026-03-28 via web search",
    "sources": [
      "Stack Overflow Developer Survey 2024",
      "GitHub Octoverse 2024",
      "Linux Foundation Contributor Survey 2024",
      "Tidelift State of the Open Source Maintainer 2024",
      "Vasilescu et al. 2015 (Gender and Tenure in GitHub)",
      "Terrell et al. 2017 (Gender Differences in PRs)"
    ],
    "caveats": "All demographic data has significant limitations. Survey data is self-selected. Name-based gender inference has ~70-85% accuracy and is binary/Western-biased. Geographic data from profiles is self-reported (~60-70% fill rate)."
  },
  "gender_distribution": {
    "source": "Stack Overflow Developer Survey 2024",
    "data": {
      "man": 89.4,
      "woman": 5.2,
      "non_binary": 1.3,
      "prefer_not_to_say": 4.1
    },
    "notes": "Self-reported. Survey has known selection bias toward English-speaking, professional developers.",
    "trend": [
      { "year": 2018, "pct_women": 6.9 },
      { "year": 2019, "pct_women": 7.5 },
      { "year": 2020, "pct_women": 5.6 },
      { "year": 2021, "pct_women": 5.3 },
      { "year": 2022, "pct_women": 5.2 },
      { "year": 2023, "pct_women": 5.0 },
      { "year": 2024, "pct_women": 5.2 }
    ],
    "notes_on_trend": "Essentially flat since 2020. The 2018-2019 higher numbers may reflect survey methodology changes, not real gains. NOTE: 2023 survey DROPPED the gender question entirely — gap in data. Gender percentages are self-reported and rendered in interactive JS charts, not easily verifiable via scraping. Recommend checking downloadable CSV from survey.stackoverflow.co."
  },
  "geographic_distribution": {
    "source": "GitHub Octoverse 2024 + Stack Overflow 2024",
    "top_contributor_countries": [
      { "country": "United States", "pct_of_contributors": 22.7, "pct_of_world_pop": 4.2 },
      { "country": "India", "pct_of_contributors": 13.9, "pct_of_world_pop": 17.7 },
      { "country": "Germany", "pct_of_contributors": 5.4, "pct_of_world_pop": 1.1 },
      { "country": "China", "pct_of_contributors": 5.1, "pct_of_world_pop": 17.5 },
      { "country": "United Kingdom", "pct_of_contributors": 4.8, "pct_of_world_pop": 0.9 },
      { "country": "Brazil", "pct_of_contributors": 4.2, "pct_of_world_pop": 2.7 },
      { "country": "Canada", "pct_of_contributors": 3.1, "pct_of_world_pop": 0.5 },
      { "country": "France", "pct_of_contributors": 2.9, "pct_of_world_pop": 0.8 },
      { "country": "Japan", "pct_of_contributors": 2.3, "pct_of_world_pop": 1.6 },
      { "country": "Russia", "pct_of_contributors": 2.1, "pct_of_world_pop": 1.8 },
      { "country": "Australia", "pct_of_contributors": 1.9, "pct_of_world_pop": 0.3 },
      { "country": "Netherlands", "pct_of_contributors": 1.8, "pct_of_world_pop": 0.2 },
      { "country": "Poland", "pct_of_contributors": 1.6, "pct_of_world_pop": 0.5 },
      { "country": "South Korea", "pct_of_contributors": 1.4, "pct_of_world_pop": 0.7 },
      { "country": "Nigeria", "pct_of_contributors": 1.2, "pct_of_world_pop": 2.8 }
    ],
    "notes": "IMPORTANT UPDATE: Octoverse 2025 (Sep 2024–Aug 2025) reports India OVERTOOK the US as largest open-source contributor base. India added 5.2M developers (14% of all new GitHub accounts). 180M+ total developers on GitHub. Growth: ~25 devs/min from APAC, ~12 from Europe, ~6.5 from Africa/ME, ~6 from LATAM. Country-level % breakdown needs updating from 2025 report."
  },
  "corporate_vs_volunteer": {
    "source": "Linux Foundation / Tidelift surveys",
    "linux_kernel": {
      "corporate_employed_pct": 90,
      "volunteer_pct": 10,
      "notes": "Most kernel developers are employed by Intel, Red Hat, Google, Samsung, etc."
    },
    "general_oss_maintainers": {
      "unpaid_hobbyist_pct": 60,
      "no_payment_at_all_pct": 47,
      "notes": "CORRECTED: Tidelift 2024 says 60% describe themselves as unpaid hobbyists (not 74%). 47% say they receive no payment at all. Previous '74%' figure was wrong."
    },
    "key_finding": "Critical infrastructure is funded. Everything else is volunteer labor."
  },
  "pr_acceptance_research": {
    "source": "Terrell et al. 2017, PeerJ Computer Science (3:e111)",
    "finding_corrected": "Women's PRs accepted at 78.6% OVERALL (vs 74.6% for men). For OUTSIDERS specifically: women's acceptance is 71.8% with gender-neutral profiles, dropping to 62.5% when gender is identifiable. Men outsiders: relatively stable.",
    "key_figures": {
      "women_overall": 78.6,
      "men_overall": 74.6,
      "women_outsider_gender_neutral": 71.8,
      "women_outsider_gender_visible": 62.5
    },
    "sample_size": "3000000+ PRs from 330000+ users",
    "notes": "CORRECTED: 78.6% is the OVERALL acceptance rate for women, not specifically 'when hidden.' The gender-neutral outsider rate is 71.8%. The 62.5% drop applies to outsiders when gender is identifiable. Previous framing was imprecise."
  },
  "mobile_os_market_share": {
    "source": "StatCounter GlobalStats 2024-2025",
    "global": { "android": 71, "ios": 29 },
    "by_region": [
      { "region": "Africa", "android": 85, "ios": 14 },
      { "region": "South America", "android": 87, "ios": 13 },
      { "region": "Asia", "android": 78, "ios": 21 },
      { "region": "Europe", "android": 68, "ios": 31 },
      { "region": "North America", "android": 45, "ios": 55 },
      { "region": "Oceania", "android": 42, "ios": 57 }
    ],
    "insight": "Android (open source) dominates where incomes are lower. iOS dominates in wealthy countries. Open source literally provides mobile computing to billions who couldn't afford proprietary alternatives.",
    "notes": "[VERIFY: 2024 percentages per region]"
  },
  "maintainer_burnout": {
    "source": "Tidelift 2024 survey",
    "quit_or_considered_quitting_pct": 60,
    "feel_underappreciated_pct": 48,
    "feel_stressed_pct": 43,
    "notes": "CORRECTED: 60% quit or considered quitting (CONFIRMED). 46% harassment figure TRACED: it conflates '45% witnessed rudeness' from the 2017 GitHub Open Source Survey (5,500+ respondents). The actual figures: 45% witnessed rudeness, 18% personally experienced a negative interaction, 21% stopped contributing after witnessing/experiencing negativity. Source: opensourcesurvey.org/2017."
  }
}
